pyredlock/__init__.py
pyredlock/redis_client.py
pyredlock/redlock.py
pyredlock/test_redlock.py
pyredlock/test_redlock_async.py
pyredlock-1.0.0.dist-info/LICENSE.txt
pyredlock-1.0.0.dist-info/METADATA
pyredlock-1.0.0.dist-info/WHEEL
pyredlock-1.0.0.dist-info/top_level.txt
pyredlock-1.0.0.dist-info/RECORD
