Metadata-Version: 2.1
Name: pyredlock
Version: 1.0.0
Summary: A Redis distributed lock implementation in Python
Home-page: https://github.com/amazingchow/redlock-py
Author: Adam Zhou
Author-email: adamzhouisnothing@gmail.com
Classifier: Development Status :: 5 - Production/Stable
Classifier: Intended Audience :: Developers
Classifier: License :: OSI Approved :: MIT License
Classifier: Programming Language :: Python :: 3
Classifier: Programming Language :: Python :: 3.6
Classifier: Programming Language :: Python :: 3.7
Classifier: Programming Language :: Python :: 3.8
License-File: LICENSE.txt
Requires-Dist: jsonschema ==4.20.0
Requires-Dist: loguru ==0.7.2
Requires-Dist: redis ==5.0.1
